gstools_core-1.2.0.dist-info/METADATA
gstools_core-1.2.0.dist-info/WHEEL
gstools_core-1.2.0.dist-info/licenses/LICENSE
gstools_core/__init__.py
gstools_core/gstools_core.pyd
gstools_core-1.2.0.dist-info/RECORD
