Metadata-Version: 2.4
Name: gstools-core
Version: 1.2.0
Classifier: Development Status :: 5 - Production/Stable
Classifier: Intended Audience :: Developers
Classifier: Intended Audience :: End Users/Desktop
Classifier: Intended Audience :: Science/Research
Classifier: Intended Audience :: Education
Classifier: License :: OSI Approved :: GNU Lesser General Public License v3 (LGPLv3)
Classifier: Natural Language :: English
Classifier: Programming Language :: Python
Classifier: Programming Language :: Python :: 3
Classifier: Programming Language :: Python :: 3 :: Only
Classifier: Programming Language :: Python :: 3.8
Classifier: Programming Language :: Python :: 3.9
Classifier: Programming Language :: Python :: 3.10
Classifier: Programming Language :: Python :: 3.11
Classifier: Programming Language :: Python :: 3.12
Classifier: Programming Language :: Python :: 3.13
Classifier: Topic :: Scientific/Engineering
Classifier: Topic :: Scientific/Engineering :: GIS
Classifier: Topic :: Scientific/Engineering :: Hydrology
Classifier: Topic :: Scientific/Engineering :: Mathematics
Classifier: Topic :: Scientific/Engineering :: Physics
Classifier: Topic :: Utilities
Requires-Dist: numpy>=1.20.0
License-File: LICENSE
Home-Page: https://geostat-framework.org/#gstools
Requires-Python: >=3.8
Project-URL: Homepage, https://geostat-framework.org/#gstools
Project-URL: Documentation, https://github.com/GeoStat-Framework/GSTools-Core
Project-URL: Source, https://github.com/GeoStat-Framework/GSTools-Core
Project-URL: Changelog, https://github.com/GeoStat-Framework/GSTools-Core/commits
Project-URL: Tracker, https://github.com/GeoStat-Framework/GSTools-Core/issues
